akmaddition/__init__.py
akmaddition/addition.py
akmaddition/operations.py
akmaddition-1.0.0.dist-info/LICENSE
akmaddition-1.0.0.dist-info/METADATA
akmaddition-1.0.0.dist-info/WHEEL
akmaddition-1.0.0.dist-info/top_level.txt
akmaddition-1.0.0.dist-info/RECORD
