Metadata-Version: 2.1
Name: akmaddition
Version: 1.0.0
Summary: AKM Addition Package
Home-page: https://github.com/vishal-meshram/akmaddition.git
Author: akm
Author-email: akm@gmail.com
Classifier: Programming Language :: Python :: 3
Classifier: License :: OSI Approved :: MIT License
Classifier: Operating System :: OS Independent
Requires-Python: >=3.6
License-File: LICENSE
